whatsappchatbot/__init__.py
whatsappchatbot/extract_chats.py
whatsappchatbot/response.py
whatsappchatbot/selenium_automation.py
whatsappchatbot/whatsappChatbot.py
whatsappchatbot-0.0.5.dist-info/LICENSE
whatsappchatbot-0.0.5.dist-info/METADATA
whatsappchatbot-0.0.5.dist-info/WHEEL
whatsappchatbot-0.0.5.dist-info/top_level.txt
whatsappchatbot-0.0.5.dist-info/RECORD
